jupyterlab_gt_coar_theme/__init__.py
jupyterlab_gt_coar_theme/_version.py
jupyterlab_gt_coar_theme/labextensions/dark/package.json
jupyterlab_gt_coar_theme/labextensions/dark/static/321.9ef5e03b285ce4912801.js
jupyterlab_gt_coar_theme/labextensions/dark/static/480.ed9735bfa133045ef4d5.js
jupyterlab_gt_coar_theme/labextensions/dark/static/568.23ae929d7affb01a3162.js
jupyterlab_gt_coar_theme/labextensions/dark/static/remoteEntry.f21c2a6e503f28428f53.js
jupyterlab_gt_coar_theme/labextensions/dark/static/style.js
jupyterlab_gt_coar_theme/labextensions/dark/static/_/brand/style/img/chevrons.svg
jupyterlab_gt_coar_theme/labextensions/dark/static/_/brand/style/img/wordmark.svg
jupyterlab_gt_coar_theme/labextensions/dark/themes/@gt-coar/jupyterlab-theme-dark/index.css
jupyterlab_gt_coar_theme/labextensions/dark/themes/@gt-coar/jupyterlab-theme-dark/index.js
jupyterlab_gt_coar_theme/labextensions/light/package.json
jupyterlab_gt_coar_theme/labextensions/light/static/480.fda9bcf3d2158cb1187d.js
jupyterlab_gt_coar_theme/labextensions/light/static/568.1a748d02bcc61c3669c8.js
jupyterlab_gt_coar_theme/labextensions/light/static/remoteEntry.274ff050638686e45c93.js
jupyterlab_gt_coar_theme/labextensions/light/static/style.js
jupyterlab_gt_coar_theme/labextensions/light/themes/@gt-coar/jupyterlab-theme-light/index.css
jupyterlab_gt_coar_theme/labextensions/light/themes/@gt-coar/jupyterlab-theme-light/index.js
jupyterlab_gt_coar_theme-0.3.0.data/data/share/jupyter/labextensions/@gt-coar/jupyterlab-theme-dark/package.json
jupyterlab_gt_coar_theme-0.3.0.data/data/share/jupyter/labextensions/@gt-coar/jupyterlab-theme-dark/static/321.9ef5e03b285ce4912801.js
jupyterlab_gt_coar_theme-0.3.0.data/data/share/jupyter/labextensions/@gt-coar/jupyterlab-theme-dark/static/480.ed9735bfa133045ef4d5.js
jupyterlab_gt_coar_theme-0.3.0.data/data/share/jupyter/labextensions/@gt-coar/jupyterlab-theme-dark/static/568.23ae929d7affb01a3162.js
jupyterlab_gt_coar_theme-0.3.0.dist-info/LICENSE.txt
jupyterlab_gt_coar_theme-0.3.0.dist-info/METADATA
jupyterlab_gt_coar_theme-0.3.0.dist-info/WHEEL
jupyterlab_gt_coar_theme-0.3.0.dist-info/top_level.txt
jupyterlab_gt_coar_theme-0.3.0.dist-info/RECORD
