Metadata-Version: 2.1
Name: jupyterlab-gt-coar-theme
Version: 0.3.0
Summary: an unofficial Georgia Tech theme for JupyterLab
Home-page: https://github.com/gt-coar/jupyterlab-gt-coar-theme
Author: jupyterlab-gt-coar-theme contributors
Author-email: coar@gaetch.edu
License: BSD-3-Clause
Project-URL: Bug Tracker, https://github.com/gt-coar/jupyterlab-gt-coar-theme/issues
Project-URL: Source Code, https://github.com/gt-coar/jupyterlab-gt-coar-theme
Platform: UNKNOWN
Classifier: Intended Audience :: Developers
Classifier: Intended Audience :: Science/Research
Classifier: License :: OSI Approved :: BSD License
Classifier: Programming Language :: Python
Classifier: Programming Language :: Python :: 3
Classifier: Programming Language :: Python :: 3.6
Classifier: Programming Language :: Python :: 3.7
Classifier: Programming Language :: Python :: 3.8
Classifier: Programming Language :: Python :: 3.9
Classifier: Framework :: Jupyter
Requires-Python: >=3.6
License-File: LICENSE.txt
Requires-Dist: jupyterlab (<4,>=3)
Provides-Extra: dev
Requires-Dist: black ; extra == 'dev'
Requires-Dist: flake8 ; extra == 'dev'
Requires-Dist: isort ; extra == 'dev'
Requires-Dist: pyflakes ; extra == 'dev'
Requires-Dist: wheel ; extra == 'dev'
Requires-Dist: twine ; extra == 'dev'
Requires-Dist: doit ; extra == 'dev'
Provides-Extra: lint
Requires-Dist: black ; extra == 'lint'
Requires-Dist: flake8 ; extra == 'lint'
Requires-Dist: isort ; extra == 'lint'
Requires-Dist: pyflakes ; extra == 'lint'
